ipygany/__init__.py
ipygany/_frontend.py
ipygany/_version.py
ipygany/colormaps.py
ipygany/ipygany.py
ipygany/serialization.py
ipygany/vtk_loader.py
ipygany/labextension/package.json
ipygany/labextension/static/153.731cf064a717b2eec68e.js
ipygany/labextension/static/212.690d496fa9aec8e06518.js
ipygany/labextension/static/272.0fad1645beca2ed49f5e.js
ipygany/labextension/static/272.0fad1645beca2ed49f5e.js.LICENSE.txt
ipygany/labextension/static/367.2d66e682401e2340a8d4.js
ipygany/labextension/static/480.fd8a269df5f1e8d47180.js
ipygany/labextension/static/539.f99c703890c957d631ec.js
ipygany/labextension/static/568.2dac415045ba52492f12.js
ipygany/labextension/static/remoteEntry.8d04f4bf19b3ea22cbf5.js
ipygany/labextension/static/style.js
ipygany/nbextension/__init__.py
ipygany/nbextension/static/extension.js
ipygany/nbextension/static/index.js
ipygany/nbextension/static/index.js.LICENSE.txt
ipygany/nbextension/static/index.js.map
ipygany-0.5.0.data/data/etc/jupyter/nbconfig/notebook.d/ipygany.json
ipygany-0.5.0.data/data/share/jupyter/labextensions/ipygany/package.json
ipygany-0.5.0.data/data/share/jupyter/labextensions/ipygany/static/153.731cf064a717b2eec68e.js
ipygany-0.5.0.data/data/share/jupyter/labextensions/ipygany/static/212.690d496fa9aec8e06518.js
ipygany-0.5.0.data/data/share/jupyter/labextensions/ipygany/static/272.0fad1645beca2ed49f5e.js
ipygany-0.5.0.data/data/share/jupyter/labextensions/ipygany/static/272.0fad1645beca2ed49f5e.js.LICENSE.txt
ipygany-0.5.0.data/data/share/jupyter/labextensions/ipygany/static/367.2d66e682401e2340a8d4.js
ipygany-0.5.0.data/data/share/jupyter/labextensions/ipygany/static/480.fd8a269df5f1e8d47180.js
ipygany-0.5.0.data/data/share/jupyter/labextensions/ipygany/static/539.f99c703890c957d631ec.js
ipygany-0.5.0.data/data/share/jupyter/labextensions/ipygany/static/568.2dac415045ba52492f12.js
ipygany-0.5.0.data/data/share/jupyter/labextensions/ipygany/static/remoteEntry.8d04f4bf19b3ea22cbf5.js
ipygany-0.5.0.dist-info/LICENSE.txt
ipygany-0.5.0.dist-info/METADATA
ipygany-0.5.0.dist-info/WHEEL
ipygany-0.5.0.dist-info/top_level.txt
ipygany-0.5.0.dist-info/RECORD
